adkx/__init__.py
adkx/py.typed
adkx-0.0.3.dist-info/licenses/LICENSE
adkx-0.0.3.dist-info/WHEEL
adkx-0.0.3.dist-info/METADATA
adkx-0.0.3.dist-info/RECORD
